stockchart_mcp_server/__init__.py
stockchart_mcp_server/__main__.py
stockchart_mcp_server/server.py
stockchart_mcp_server-0.1.4.dist-info/METADATA
stockchart_mcp_server-0.1.4.dist-info/WHEEL
stockchart_mcp_server-0.1.4.dist-info/entry_points.txt
stockchart_mcp_server-0.1.4.dist-info/RECORD
