Metadata-Version: 2.4
Name: stockchart-mcp-server
Version: 0.1.4
Summary: Add your description here
Author-email: tykimos <taeyoung.kim.profile@gmail.com>
Requires-Python: >=3.11
Requires-Dist: build>=1.2.2.post1
Requires-Dist: matplotlib>=3.10.3
Requires-Dist: mcp>=1.10.1
Requires-Dist: pandas>=2.3.0
Requires-Dist: twine>=6.1.0
Requires-Dist: yfinance>=0.2.63
